napari_explorer/__init__.py
napari_explorer/_version.py
napari_explorer/_widget.py
napari_explorer/napari.yaml
napari_explorer/_tests/__init__.py
napari_explorer/_tests/test_widget.py
napari_explorer-0.0.5.dist-info/licenses/LICENSE
napari_explorer-0.0.5.dist-info/METADATA
napari_explorer-0.0.5.dist-info/WHEEL
napari_explorer-0.0.5.dist-info/entry_points.txt
napari_explorer-0.0.5.dist-info/top_level.txt
napari_explorer-0.0.5.dist-info/RECORD
